timecopilot_tirex-0.1.0.dist-info/licenses/LICENSE
tirex/__init__.py
tirex/base.py
tirex/api_adapter/__init__.py
tirex/api_adapter/forecast.py
tirex/api_adapter/gluon.py
tirex/api_adapter/hf_data.py
tirex/api_adapter/standard_adapter.py
tirex/models/__init__.py
tirex/models/components.py
tirex/models/mixed_stack.py
tirex/models/predict_utils.py
tirex/models/tirex.py
timecopilot_tirex-0.1.0.dist-info/METADATA
timecopilot_tirex-0.1.0.dist-info/WHEEL
timecopilot_tirex-0.1.0.dist-info/top_level.txt
timecopilot_tirex-0.1.0.dist-info/RECORD
