Metadata-Version: 2.4
Name: timecopilot-tirex
Version: 0.1.0
Summary: A pre-trained Time Series Forecasting Model based on xLSTM supporting zero-shot forecasting
License: NXAI COMMUNITY LICENSE AGREEMENT
Keywords: TiRex,xLSTM,Time Series,Zero-shot,Deep Learning
Classifier: Programming Language :: Python :: 3
Classifier: Operating System :: OS Independent
Requires-Python: >=3.11
License-File: LICENSE
Requires-Dist: torch
Requires-Dist: torchvision
Requires-Dist: xlstm
Requires-Dist: einops
Requires-Dist: ninja
Requires-Dist: huggingface-hub
Requires-Dist: lightning
Requires-Dist: numpy
Requires-Dist: pandas
Requires-Dist: dacite
Requires-Dist: tqdm
Provides-Extra: notebooks
Requires-Dist: ipykernel; extra == "notebooks"
Provides-Extra: gluonts
Requires-Dist: gluonts; extra == "gluonts"
Provides-Extra: hfdataset
Requires-Dist: datasets; extra == "hfdataset"
Provides-Extra: all
Requires-Dist: ipykernel; extra == "all"
Requires-Dist: gluonts; extra == "all"
Requires-Dist: datasets; extra == "all"
Dynamic: license-file
